examexam/__about__.py
examexam/__init__.py
examexam/__main__.py
examexam/config.py
examexam/constants.py
examexam/convert_to_pretty.py
examexam/find_the_toml.py
examexam/generate_questions.py
examexam/generate_study_plan.py
examexam/generate_topic_research.py
examexam/jinja_management.py
examexam/logging_config.py
examexam/py.typed
examexam/take_exam.py
examexam/validate_questions.py
examexam/apis/__init__.py
examexam/apis/conversation_and_router.py
examexam/apis/third_party_apis.py
examexam/apis/types.py
examexam/apis/utilities.py
examexam/prompts/answer_question.md.j2
examexam/prompts/evaluate_question.md.j2
examexam/prompts/generate.md.j2
examexam/prompts/study_guide.md.j2
examexam/utils/__init__.py
examexam/utils/cli_suggestions.py
examexam/utils/custom_exceptions.py
examexam/utils/secure_random.py
examexam/utils/toml_normalize.py
examexam/utils/toml_reader.py
examexam/utils/update_checker.py
examexam/utils/urllib3_helper.py
examexam-0.1.8.dist-info/METADATA
examexam-0.1.8.dist-info/WHEEL
examexam-0.1.8.dist-info/entry_points.txt
examexam-0.1.8.dist-info/licenses/LICENSE
examexam-0.1.8.dist-info/RECORD
